[
  {
    "link_it": "https://github.com/lmbstudiocontact/lv_dmean_3500_it_0/raw/main/blood_lv_dmean_3500_it.json",
    "id_item": "blood_lv_dmean_3500_it",
    "id_album": "570943489",
    "english": "blood",
    "list_mean": [
      "máu, huyết",
      "nhựa (cây); nước ngọt (hoa quả...)",
      "sự tàn sát, sự chém giết, sự đổ máu",
      "tính khí",
      "giống nòi, dòng dõi, họ hàng, gia đình",
      "người lịch sự, người ăn diện ( (thường) young blood )",
      "trích máu",
      "(săn bắn) luyện cho (chó săn) thích máu",
      "(nghĩa bóng) xúi giục, kích động (ai)"
    ],
    "hash_code_list_mean": "-1784070080",
    "list_img": [
      {
        "link_thumb": "https://live.staticflickr.com/65535/51809328971_bf2ec68213_n.jpg",
        "link_img": "https://live.staticflickr.com/65535/51809328971_6d1130c271_o.png",
        "id_image": "blood_1548345"
      },
      {
        "link_thumb": "https://live.staticflickr.com/65535/51809684019_a57705b5e8_n.jpg",
        "link_img": "https://live.staticflickr.com/65535/51809684019_fac96838e0_o.png",
        "id_image": "blood_205916"
      },
      {
        "link_thumb": "https://live.staticflickr.com/65535/51808373667_4a17d52d48_n.jpg",
        "link_img": "https://live.staticflickr.com/65535/51808373667_af5f6b3d5e_o.png",
        "id_image": "blood_2904539"
      }
    ],
    "hash_code_list_img": "1310624089",
    "list_example": [
      "dauntlessness runs in the blood of that family"
    ],
    "hash_code_list_example": "-1975683747"
  },
  {
    "link_it": "https://github.com/lmbstudiocontact/lv_dmean_3500_it_1/raw/main/duct_lv_dmean_3500_it.json",
    "id_item": "duct_lv_dmean_3500_it",
    "id_album": "570943489",
    "english": "duct",
    "list_mean": [
      "ống, ống dẫn"
    ],
    "hash_code_list_mean": "-1048614702",
    "list_img": [
      {
        "link_thumb": "https://live.staticflickr.com/65535/51808380677_03bcf18a48_n.jpg",
        "link_img": "https://live.staticflickr.com/65535/51808380677_05ffb72c7a_o.png",
        "id_image": "duct_4752685"
      }
    ],
    "hash_code_list_img": "1557571654",
    "list_example": [
      "biliary duct"
    ],
    "hash_code_list_example": "-1642016867"
  },
  {
    "link_it": "https://github.com/lmbstudiocontact/lv_dmean_3500_it_0/raw/main/centre_lv_dmean_3500_it.json",
    "id_item": "centre_lv_dmean_3500_it",
    "id_album": "570943489",
    "english": "centre",
    "list_mean": [
      "điểm có khoảng cách đều nhau với tất cả các cạnh của cái gì; điểm hoặc bộ phận chính giữa của cái gì; tâm; trung tâm",
      "điểm mà sự quan tâm của mọi người đều hướng vào",
      "nơi chính quyền được tổ chức",
      "nơi tập trung một số hoạt động hoặc phương tiện thuận lợi",
      "(thể dục,thể thao) trung phong (bóng đá)",
      "(thể dục,thể thao) cú đá hoặc đánh từ biên vào giữa",
      "(chính trị) đảng hoặc lập trường chính trị ôn hoà (ở giữa cực tả và cực hữu); phái giữa",
      "(quân sự) đạo trung quân",
      "(kỹ thuật) mẫu, dưỡng (dùng trong luyện kim)",
      "(kiến trúc) khung tò vò, khung bán nguyệt (bằng gỗ, dùng khi xây dựng)",
      "đặt cái gì vào giữa; đặt cái gì vào trung tâm",
      "(thể dục thể thao) đá hoặc đánh (quả bóng) từ biên vào giữa"
    ],
    "hash_code_list_mean": "1656323832",
    "list_img": [
      {
        "link_thumb": "https://live.staticflickr.com/65535/51809431598_1af48c55e2_n.jpg",
        "link_img": "https://live.staticflickr.com/65535/51809431598_370df73f79_o.png",
        "id_image": "centre_168654"
      },
      {
        "link_thumb": "https://live.staticflickr.com/65535/51809671324_38a2610054_n.jpg",
        "link_img": "https://live.staticflickr.com/65535/51809671324_300f8d91d9_o.png",
        "id_image": "centre_2994355"
      }
    ],
    "hash_code_list_img": "-1536641645",
    "list_example": [
      "the centre of a circle",
      "the centre of London",
      "centre of gravity",
      "children like to be the centre of attention",
      "a centre of power",
      "a centre of industry , commerce , the steel trade",
      "to centre the teapot on the table"
    ],
    "hash_code_list_example": "-1380687065"
  },
  {
    "link_it": "https://github.com/lmbstudiocontact/lv_dmean_3500_it_3/raw/main/throne_lv_dmean_3500_it.json",
    "id_item": "throne_lv_dmean_3500_it",
    "id_album": "570943489",
    "english": "throne",
    "list_mean": [
      "ngai, ngai vàng (ghế, chỗ ngồi đặc biệt của vua.. trong các nghi lễ)",
      "( the throne ) ngôi, ngôi vua (quyền lực của nhà vua)",
      "đưa lên ngôi, tôn làm vua"
    ],
    "hash_code_list_mean": "737645681",
    "list_img": [
      {
        "link_thumb": "https://live.staticflickr.com/65535/51809463633_fef51fa975_n.jpg",
        "link_img": "https://live.staticflickr.com/65535/51809463633_27db0a70e5_o.png",
        "id_image": "throne_1426773"
      },
      {
        "link_thumb": "https://live.staticflickr.com/65535/51808393662_063ffcdfcb_n.jpg",
        "link_img": "https://live.staticflickr.com/65535/51808393662_fa9e3276d6_o.png",
        "id_image": "throne_1835104"
      }
    ],
    "hash_code_list_img": "1122199941",
    "list_example": [
      "to come to the throne",
      "to succeed to the throne",
      "to lose one's throne"
    ],
    "hash_code_list_example": "-274853657"
  },
  {
    "link_it": "https://github.com/lmbstudiocontact/lv_dmean_3500_it_1/raw/main/mad_lv_dmean_3500_it.json",
    "id_item": "mad_lv_dmean_3500_it",
    "id_album": "570943489",
    "english": "mad",
    "list_mean": [
      "điên, điên rồ, điên cuồng, mất trí",
      "(thông tục) bực dọc, bực bội; tức điên ruột",
      "( + about , after , for , on ) say mê điên dại, ham thích mãnh liệt",
      "vui chơi ầm ĩ",
      "liều lĩnh",
      "tức giận, giận dữ, nổi giận",
      "như madden",
      "cơn giận dữ, cơn phẫn nộ"
    ],
    "hash_code_list_mean": "1079191962",
    "list_img": [
      {
        "link_thumb": "https://live.staticflickr.com/65535/51809685709_027695f8de_n.jpg",
        "link_img": "https://live.staticflickr.com/65535/51809685709_a33e30e3cf_o.png",
        "id_image": "mad_2366540"
      },
      {
        "link_thumb": "https://live.staticflickr.com/65535/51808375272_78745c5bc4_n.jpg",
        "link_img": "https://live.staticflickr.com/65535/51808375272_e609b88889_o.png",
        "id_image": "mad_4126695"
      },
      {
        "link_thumb": "https://live.staticflickr.com/65535/51808375242_ab32684c53_n.jpg",
        "link_img": "https://live.staticflickr.com/65535/51808375242_927b0383d1_o.png",
        "id_image": "mad_5747320"
      },
      {
        "link_thumb": "https://live.staticflickr.com/65535/51809445493_e8fd66aafd_n.jpg",
        "link_img": "https://live.staticflickr.com/65535/51809445493_7cb5d722ae_o.png",
        "id_image": "mad_6066498"
      },
      {
        "link_thumb": "https://live.staticflickr.com/65535/51809330426_c1287f6a41_n.jpg",
        "link_img": "https://live.staticflickr.com/65535/51809330426_d66a227ddf_o.png",
        "id_image": "mad_6300341"
      }
    ],
    "hash_code_list_img": "-1770072144",
    "list_example": [
      "to be mad about (at ) missing the train",
      "to be mad on music",
      "mad venture"
    ],
    "hash_code_list_example": "-1425678210"
  },
  {
    "link_it": "https://github.com/lmbstudiocontact/lv_dmean_3500_it_2/raw/main/rank_lv_dmean_3500_it.json",
    "id_item": "rank_lv_dmean_3500_it",
    "id_album": "570943489",
    "english": "rank",
    "list_mean": [
      "vị trí trong thang bậc về trách nhiệm, phẩm chất, địa vị xã hội...; hàng, cấp; chức",
      "vị trí hoặc cấp bậc trong lực lượng vũ trang; cấp bậc",
      "hàng hoặc dãy đồ đạc",
      "hàng hoặc dãy lính, cảnh sát... đứng sát cạnh nhau",
      "( to rank somebody / something as something ) xếp ai/cái gì vào hàng ngũ, phân thành cấp bậc theo phẩm chất, thành tích...; xếp loại",
      "có cấp bậc hoặc xếp vị trí",
      "rậm rạp, sum sê",
      "(nói về đất) có nhiều cỏ dại; có thể sinh nhiều cỏ dại",
      "có mùi hôi thối, có vị hôi thối; khó chịu",
      "không lầm vào đâu được; rõ rành rành"
    ],
    "hash_code_list_mean": "-1542535451",
    "list_img": [
      {
        "link_thumb": "https://live.staticflickr.com/65535/51810075870_a973207fce_n.jpg",
        "link_img": "https://live.staticflickr.com/65535/51810075870_e153be16d4_o.png",
        "id_image": "rank_2344540"
      },
      {
        "link_thumb": "https://live.staticflickr.com/65535/51809694029_5585902421_n.jpg",
        "link_img": "https://live.staticflickr.com/65535/51809694029_8a05b147b3_o.png",
        "id_image": "rank_265796"
      },
      {
        "link_thumb": "https://live.staticflickr.com/65535/51808383772_0f62356f1a_n.jpg",
        "link_img": "https://live.staticflickr.com/65535/51808383772_b67ab7e8d1_o.png",
        "id_image": "rank_942357"
      }
    ],
    "hash_code_list_img": "1246751773",
    "list_example": [
      "promoted to the rank of captain",
      "rank and file",
      "where /how do you rank Karpow as a chess player ?",
      "to rank someone among the great writers",
      "I rank her achievement very highly",
      "to rank among the best",
      "to rank first in production of coal",
      "does he rank among /with the failures ?",
      "rank vegetation",
      "rank ivy /grass",
      "rank soil",
      "a field rank with nettles and thistles",
      "rank tobacco",
      "the rank stench of rotting meat",
      "a rank lie",
      "a rank duffer",
      "rank insolence /stupidity /injustice",
      "the winning horse was a rank outsider"
    ],
    "hash_code_list_example": "-706505449"
  },
  {
    "link_it": "https://github.com/lmbstudiocontact/lv_dmean_3500_it_0/raw/main/ancient_lv_dmean_3500_it.json",
    "id_item": "ancient_lv_dmean_3500_it",
    "id_album": "570943489",
    "english": "ancient",
    "list_mean": [
      "xưa, cổ",
      "già, cao tuổi",
      "the ancients người La Mã và Hy lạp cổ đại",
      "(từ cổ,nghĩa cổ) lá cờ, cờ hiệu; người cầm cờ hiệu",
      "(từ Mỹ,nghĩa Mỹ) tác giả cổ điển"
    ],
    "hash_code_list_mean": "745653179",
    "list_img": [
      {
        "link_thumb": "https://live.staticflickr.com/65535/51809312921_285c562e67_n.jpg",
        "link_img": "https://live.staticflickr.com/65535/51809312921_ce2d5fe23e_o.png",
        "id_image": "ancient_2446833"
      },
      {
        "link_thumb": "https://live.staticflickr.com/65535/51809312996_dcf07ab7c6_n.jpg",
        "link_img": "https://live.staticflickr.com/65535/51809312996_343b1b6eb4_o.png",
        "id_image": "ancient_306829"
      },
      {
        "link_thumb": "https://live.staticflickr.com/65535/51810049395_fd5d669ea8_n.jpg",
        "link_img": "https://live.staticflickr.com/65535/51810049395_b3d2b0b0a0_o.png",
        "id_image": "ancient_3883031"
      },
      {
        "link_thumb": "https://live.staticflickr.com/65535/51809312956_1b6433d69a_n.jpg",
        "link_img": "https://live.staticflickr.com/65535/51809312956_6244b3be2d_o.png",
        "id_image": "ancient_499250"
      }
    ],
    "hash_code_list_img": "-1013010472",
    "list_example": [
      "ancient Rome",
      "ancient world",
      "ancient history",
      "ancient monument"
    ],
    "hash_code_list_example": "1751675249"
  },
  {
    "link_it": "https://github.com/lmbstudiocontact/lv_dmean_3500_it_2/raw/main/prosthetic_lv_dmean_3500_it.json",
    "id_item": "prosthetic_lv_dmean_3500_it",
    "id_album": "570943489",
    "english": "prosthetic",
    "list_mean": [
      "(y học) (thuộc) sự lắp bộ phận giả"
    ],
    "hash_code_list_mean": "1519447565",
    "list_img": [
      {
        "link_thumb": "https://live.staticflickr.com/65535/51809350316_21d8eecc63_n.jpg",
        "link_img": "https://live.staticflickr.com/65535/51809350316_771e2895d1_o.png",
        "id_image": "prosthetic_1467309"
      },
      {
        "link_thumb": "https://live.staticflickr.com/65535/51808395077_1b378e5e3a_n.jpg",
        "link_img": "https://live.staticflickr.com/65535/51808395077_4ff636972f_o.png",
        "id_image": "prosthetic_4198354"
      },
      {
        "link_thumb": "https://live.staticflickr.com/65535/51808395062_cfa6c60826_n.jpg",
        "link_img": "https://live.staticflickr.com/65535/51808395062_6a0cbe4a82_o.png",
        "id_image": "prosthetic_4215377"
      }
    ],
    "hash_code_list_img": "-1150396960",
    "list_example": [
      "a prosthetic appliance"
    ],
    "hash_code_list_example": "-1609880146"
  },
  {
    "link_it": "https://github.com/lmbstudiocontact/lv_dmean_3500_it_1/raw/main/gas_lv_dmean_3500_it.json",
    "id_item": "gas_lv_dmean_3500_it",
    "id_album": "570943489",
    "english": "gas",
    "list_mean": [
      "khí",
      "khí thắp, hơi đốt",
      "khí tê khi chữa răng ( (cũng) laughing gas )",
      "(quân sự) hơi độc, hơi ngạt",
      "khí nổ (mỏ, than)",
      "(từ Mỹ,nghĩa Mỹ), (thông tục) dầu xăng",
      "(thông tục) chuyện rỗng tuếch không đâu vào đâu, chuyện tầm phào; chuyện huyên hoang khoác lác",
      "cung cấp khí thấp, cung cấp hơi đốt (cho một căn buồng)",
      "hơ (chỉ, sợi...) qua đèn khí (cho hết lông tơ)",
      "thắp sáng bằng đèn khí",
      "thả hơi độc, thả hơi ngạt, làm ngạt bằng hơi độc",
      "(thông tục) lừa bịp (ai) bằng những lời huênh hoang khoác lác",
      "xì hơi",
      "nói dông dài; nói chuyện tầm phào; huyên hoang khoác lác"
    ],
    "hash_code_list_mean": "1199932861",
    "list_img": [
      {
        "link_thumb": "https://live.staticflickr.com/65535/51809338401_2400af30ba_n.jpg",
        "link_img": "https://live.staticflickr.com/65535/51809338401_aa4bcf3530_o.png",
        "id_image": "gas_3365464"
      },
      {
        "link_thumb": "https://live.staticflickr.com/65535/51809453343_3e5f09e80a_n.jpg",
        "link_img": "https://live.staticflickr.com/65535/51809453343_c40f182428_o.png",
        "id_image": "gas_3523673"
      },
      {
        "link_thumb": "https://live.staticflickr.com/65535/51808383372_96424b035d_n.jpg",
        "link_img": "https://live.staticflickr.com/65535/51808383372_8d74130b48_o.png",
        "id_image": "gas_465018"
      },
      {
        "link_thumb": "https://live.staticflickr.com/65535/51810075390_cf940399a0_n.jpg",
        "link_img": "https://live.staticflickr.com/65535/51810075390_e22f87888a_o.png",
        "id_image": "gas_6315520"
      }
    ],
    "hash_code_list_img": "1971571251",
    "list_example": [
      "To gas up a plane"
    ],
    "hash_code_list_example": "-1702245053"
  },
  {
    "link_it": "https://github.com/lmbstudiocontact/lv_dmean_3500_it_1/raw/main/general_lv_dmean_3500_it.json",
    "id_item": "general_lv_dmean_3500_it",
    "id_album": "570943489",
    "english": "general",
    "list_mean": [
      "tác động đến tất cả hoặc hầu hết mọi người, mọi nơi, mọi vật; chung; phổ biến",
      "không giới hạn ở một phần hoặc một khía cạnh của con người, sự vật, hoặc ở một thời điểm cụ thể nào; toàn thể, toàn bộ, chung",
      "không chuyên sâu vào chủ đề",
      "không chuyên sâu hoặc giới hạn về phạm vi công việc, công dụng, hoạt động",
      "(thường) trong các chức danh viết hoa và đi sau danh từ; tổng",
      "bình thường; thông thường",
      "không rõ, mơ hồ",
      "cái chung, cái đại thể, cái tổng quát, toàn thể",
      "(quân sự) tướng, nhà chiến lược xuất sắc; nhà chiến thuật xuất sắc",
      "( the general ) (từ cổ,nghĩa cổ) nhân dân quần chúng",
      "(tôn giáo) trưởng tu viện",
      "người hầu đủ mọi việc ( (cũng) general servant )"
    ],
    "hash_code_list_mean": "-1676644287",
    "list_img": [
      {
        "link_thumb": "https://live.staticflickr.com/65535/51808381377_e6a1c16335_n.jpg",
        "link_img": "https://live.staticflickr.com/65535/51808381377_e99041684e_o.png",
        "id_image": "general_1461917"
      },
      {
        "link_thumb": "https://live.staticflickr.com/65535/51809691669_1b161341ff_n.jpg",
        "link_img": "https://live.staticflickr.com/65535/51809691669_023bd26878_o.png",
        "id_image": "general_2714191"
      }
    ],
    "hash_code_list_img": "2068705193",
    "list_example": [
      "a matter of general interest /concern",
      "a general lowering of standards",
      "once quite rare , they are now in general use",
      "that man's a general nuisance",
      "the general public",
      "to work for general welfare",
      "general opinion",
      "the general impression was that it had improved",
      "a general meeting",
      "a general strike",
      "a general election",
      "there is still some weakness in the legs , but her general condition is good",
      "the opening chapter gives a general view of the subject",
      "the old building was in a general state of decay /disrepair",
      "general sciences /studies",
      "general knowledge",
      "general hospital",
      "general practitioner",
      "the general reader",
      "a general factotum",
      "general dealer",
      "the general manager",
      "the general practice in such cases is to apply for a court order",
      "a general principle to which there may be several exceptions",
      "as a general rule",
      "in general , her work has been good , but this essay is dreadful",
      "his description was too general to be of much use",
      "to bear a general resemblance to somebody /something",
      "to speak /write in general terms",
      "to argue from the general to the particular",
      "the general of mankind"
    ],
    "hash_code_list_example": "-1998361211"
  },
  {
    "link_it": "https://github.com/lmbstudiocontact/lv_dmean_3500_it_1/raw/main/financial_lv_dmean_3500_it.json",
    "id_item": "financial_lv_dmean_3500_it",
    "id_album": "570943489",
    "english": "financial",
    "list_mean": [
      "(thuộc) tài chính, (về) tài chính"
    ],
    "hash_code_list_mean": "-1735449747",
    "list_img": [
      {
        "link_thumb": "https://live.staticflickr.com/65535/51809683209_ae171aafdd_n.jpg",
        "link_img": "https://live.staticflickr.com/65535/51809683209_09c55f3f8e_o.png",
        "id_image": "financial_2111182"
      },
      {
        "link_thumb": "https://live.staticflickr.com/65535/51809683154_9bb23ff41a_n.jpg",
        "link_img": "https://live.staticflickr.com/65535/51809683154_9294c2e05e_o.png",
        "id_image": "financial_3029232"
      },
      {
        "link_thumb": "https://live.staticflickr.com/65535/51810064740_b172d0a039_n.jpg",
        "link_img": "https://live.staticflickr.com/65535/51810064740_d911a5c4cc_o.png",
        "id_image": "financial_3043461"
      },
      {
        "link_thumb": "https://live.staticflickr.com/65535/51810064715_dc2ea55f60_n.jpg",
        "link_img": "https://live.staticflickr.com/65535/51810064715_2d55d3589b_o.png",
        "id_image": "financial_3449384"
      },
      {
        "link_thumb": "https://live.staticflickr.com/65535/51809683024_e91336cbf3_n.jpg",
        "link_img": "https://live.staticflickr.com/65535/51809683024_8823a41f8b_o.png",
        "id_image": "financial_4669231"
      }
    ],
    "hash_code_list_img": "2130333559",
    "list_example": [
      "a financial institute",
      "financial world",
      "financial year",
      "to be in financial difficulties"
    ],
    "hash_code_list_example": "1037016252"
  },
  {
    "link_it": "https://github.com/lmbstudiocontact/lv_dmean_3500_it_0/raw/main/discount_lv_dmean_3500_it.json",
    "id_item": "discount_lv_dmean_3500_it",
    "id_album": "570943489",
    "english": "discount",
    "list_mean": [
      "phần tiền được giảm trong giá của cái gì; tiền bớt; tiền trừ",
      "tiền được khấu trừ khi trả hối phiếu (như) rebate",
      "sự trừ hao (về mức độ xác thực của một câu chuyện, một bản tin...)",
      "mua hoặc bán một hối phiếu với giá thấp hơn giá khi đến hạn thanh toán",
      "bán hạ giá; bán giảm giá",
      "không kể đến, không đếm xỉa đến, không để ý đến; coi nhẹ; coi thường"
    ],
    "hash_code_list_mean": "-1802899332",
    "list_img": [
      {
        "link_thumb": "https://live.staticflickr.com/65535/51809432708_834f37ed0a_n.jpg",
        "link_img": "https://live.staticflickr.com/65535/51809432708_218b9f84b7_o.png",
        "id_image": "discount_1057477"
      },
      {
        "link_thumb": "https://live.staticflickr.com/65535/51810054120_a0ec00f82c_n.jpg",
        "link_img": "https://live.staticflickr.com/65535/51810054120_55a01f3a03_o.png",
        "id_image": "discount_675752"
      }
    ],
    "hash_code_list_img": "1556947144",
    "list_example": [
      "we give (a) 10% discount for cash",
      "You can discount what Jack said : He's a dreadful liar"
    ],
    "hash_code_list_example": "1405477598"
  },
  {
    "link_it": "https://github.com/lmbstudiocontact/lv_dmean_3500_it_0/raw/main/dam_lv_dmean_3500_it.json",
    "id_item": "dam_lv_dmean_3500_it",
    "id_album": "570943489",
    "english": "dam",
    "list_mean": [
      "(động vật học) vật mẹ",
      "đập (ngăn nước)",
      "nước ngăn lại, bể nước",
      "xây đập (ở nơi nào); ngăn (nước) bằng đập",
      "(nghĩa bóng) ( (thường) + up ) ghìm lại, kiềm chế lại"
    ],
    "hash_code_list_mean": "977453259",
    "list_img": [
      {
        "link_thumb": "https://live.staticflickr.com/65535/51809311596_3349a64370_n.jpg",
        "link_img": "https://live.staticflickr.com/65535/51809311596_ceb22d3d9d_o.png",
        "id_image": "dam_2321431"
      },
      {
        "link_thumb": "https://live.staticflickr.com/65535/51809311541_d1495d51a5_n.jpg",
        "link_img": "https://live.staticflickr.com/65535/51809311541_ae5a2f744b_o.png",
        "id_image": "dam_3722851"
      },
      {
        "link_thumb": "https://live.staticflickr.com/65535/51810048175_18657f3016_n.jpg",
        "link_img": "https://live.staticflickr.com/65535/51810048175_16955a6fb4_o.png",
        "id_image": "dam_5782512"
      },
      {
        "link_thumb": "https://live.staticflickr.com/65535/51809426493_ef76a28a22_n.jpg",
        "link_img": "https://live.staticflickr.com/65535/51809426493_899359629c_o.png",
        "id_image": "dam_778653"
      }
    ],
    "hash_code_list_img": "310962706",
    "list_example": [
      "to dam up one's emotion"
    ],
    "hash_code_list_example": "1035022012"
  },
  {
    "link_it": "https://github.com/lmbstudiocontact/lv_dmean_3500_it_3/raw/main/speaker_lv_dmean_3500_it.json",
    "id_item": "speaker_lv_dmean_3500_it",
    "id_album": "570943489",
    "english": "speaker",
    "list_mean": [
      "người nói, người diễn thuyết, người đọc diễn văn; diễn giả; nhà hùng biện",
      "người thuyết minh (phim)",
      "người nói một thứ tiếng nào đó",
      "(thông tục) loa phóng thanh (như) loudspeaker",
      "( the Speaker ) chủ tịch hạ nghị viện ( Anh, Mỹ)"
    ],
    "hash_code_list_mean": "968262198",
    "list_img": [
      {
        "link_thumb": "https://live.staticflickr.com/65535/51809679944_e1fb818295_n.jpg",
        "link_img": "https://live.staticflickr.com/65535/51809679944_8632aeeec4_o.png",
        "id_image": "speaker_422509"
      }
    ],
    "hash_code_list_img": "752571381",
    "list_example": [
      "French speakers /speakers of French"
    ],
    "hash_code_list_example": "-1059445569"
  },
  {
    "link_it": "https://github.com/lmbstudiocontact/lv_dmean_3500_it_1/raw/main/lottery_lv_dmean_3500_it.json",
    "id_item": "lottery_lv_dmean_3500_it",
    "id_album": "570943489",
    "english": "lottery",
    "list_mean": [
      "sự thu tiền bằng cách bán vé và tặng giải cho những người có vé được chọn ra một cách ngẫu nhiên; xổ số",
      "điều may rủi"
    ],
    "hash_code_list_mean": "580108127",
    "list_img": [
      {
        "link_thumb": "https://live.staticflickr.com/65535/51809334716_a935f16b63_n.jpg",
        "link_img": "https://live.staticflickr.com/65535/51809334716_19392d1c23_o.png",
        "id_image": "lottery_218353"
      },
      {
        "link_thumb": "https://live.staticflickr.com/65535/51809449708_9f0cc2bb03_n.jpg",
        "link_img": "https://live.staticflickr.com/65535/51809449708_22aa7715ef_o.png",
        "id_image": "lottery_218355"
      },
      {
        "link_thumb": "https://live.staticflickr.com/65535/51810071615_de35729bf8_n.jpg",
        "link_img": "https://live.staticflickr.com/65535/51810071615_fa1197125e_o.png",
        "id_image": "lottery_4658201"
      },
      {
        "link_thumb": "https://live.staticflickr.com/65535/51809449623_799777e3ee_n.jpg",
        "link_img": "https://live.staticflickr.com/65535/51809449623_c0df41b5c5_o.png",
        "id_image": "lottery_4658208"
      }
    ],
    "hash_code_list_img": "1543345153",
    "list_example": [
      "a lottery ticket"
    ],
    "hash_code_list_example": "1170489729"
  },
  {
    "link_it": "https://github.com/lmbstudiocontact/lv_dmean_3500_it_3/raw/main/swirl_lv_dmean_3500_it.json",
    "id_item": "swirl_lv_dmean_3500_it",
    "id_album": "570943489",
    "english": "swirl",
    "list_mean": [
      "( + off ) sự xoáy, sự cuộn",
      "chỗ nước xoáy, chỗ nước cuộn",
      "gió xoáy, gió lốc",
      "hình xoáy, hình xoắn",
      "cuộn, xoáy; cuốn đi",
      "làm cho cuộn, làm cho xoáy (nước, không khí..)"
    ],
    "hash_code_list_mean": "301027803",
    "list_img": [
      {
        "link_thumb": "https://live.staticflickr.com/65535/51809331856_e9f4dc3fb0_n.jpg",
        "link_img": "https://live.staticflickr.com/65535/51809331856_d0c4d9bd2f_o.png",
        "id_image": "swirl_6006266"
      }
    ],
    "hash_code_list_img": "1163979572",
    "list_example": [
      "smoke swirled up the chimney",
      "the log was swirled away downstream by the current"
    ],
    "hash_code_list_example": "-1236925702"
  },
  {
    "link_it": "https://github.com/lmbstudiocontact/lv_dmean_3500_it_1/raw/main/grin_lv_dmean_3500_it.json",
    "id_item": "grin_lv_dmean_3500_it",
    "id_album": "570943489",
    "english": "grin",
    "list_mean": [
      "cái cười xếch đến mang tai; cái cười toe toét",
      "nhe răng ra cười, cười toe toét"
    ],
    "hash_code_list_mean": "-1844846263",
    "list_img": [
      {
        "link_thumb": "https://live.staticflickr.com/65535/51810058280_24eebce5de_n.jpg",
        "link_img": "https://live.staticflickr.com/65535/51810058280_48aba99d09_o.png",
        "id_image": "grin_2977977"
      },
      {
        "link_thumb": "https://live.staticflickr.com/65535/51808366372_cc73904591_n.jpg",
        "link_img": "https://live.staticflickr.com/65535/51808366372_0775920f07_o.png",
        "id_image": "grin_2978025"
      },
      {
        "link_thumb": "https://live.staticflickr.com/65535/51809321496_1dfc379ba5_n.jpg",
        "link_img": "https://live.staticflickr.com/65535/51809321496_e260768732_o.png",
        "id_image": "grin_6259824"
      },
      {
        "link_thumb": "https://live.staticflickr.com/65535/51809321436_14c62f329c_n.jpg",
        "link_img": "https://live.staticflickr.com/65535/51809321436_45c8e700b4_o.png",
        "id_image": "grin_6259903"
      }
    ],
    "hash_code_list_img": "1551216104",
    "list_example": [
      "to grin at somebody",
      "to grin with delight",
      "to grin like a Cheshire cat",
      "to grin from ear to ear",
      "to grin and bear it"
    ],
    "hash_code_list_example": "1179937960"
  },
  {
    "link_it": "https://github.com/lmbstudiocontact/lv_dmean_3500_it_2/raw/main/sanctuary_lv_dmean_3500_it.json",
    "id_item": "sanctuary_lv_dmean_3500_it",
    "id_album": "570943489",
    "english": "sanctuary",
    "list_mean": [
      "nơi tôn nghiêm, nơi thiêng liêng; điện thờ (nhà thờ, chùa chiền)",
      "(từ Mỹ, nghĩa Mỹ) phòng diễn ra các nghi lễ tôn giáo chung; thánh đường",
      "nơi trú ẩn, nơi trốn tránh, nơi ẩn náu",
      "quyền bảo vệ những người đang bị đuổi bắt hoặc bị tấn công; quyền bảo hộ",
      "khu bảo tồn động vật hoang dã và làm cho chúng sinh sôi phát triển"
    ],
    "hash_code_list_mean": "2118134461",
    "list_img": [
      {
        "link_thumb": "https://live.staticflickr.com/65535/51809690599_38cb44c3b1_n.jpg",
        "link_img": "https://live.staticflickr.com/65535/51809690599_2afe1a87e7_o.png",
        "id_image": "sanctuary_3498689"
      },
      {
        "link_thumb": "https://live.staticflickr.com/65535/51809450358_de6f65d09e_n.jpg",
        "link_img": "https://live.staticflickr.com/65535/51809450358_2f97f07828_o.png",
        "id_image": "sanctuary_4470253"
      }
    ],
    "hash_code_list_img": "-977824269",
    "list_example": [
      "our country is a safe sanctuary for political refugees from all over the world"
    ],
    "hash_code_list_example": "-1946918901"
  },
  {
    "link_it": "https://github.com/lmbstudiocontact/lv_dmean_3500_it_2/raw/main/opportunity_lv_dmean_3500_it.json",
    "id_item": "opportunity_lv_dmean_3500_it",
    "id_album": "570943489",
    "english": "opportunity",
    "list_mean": [
      "( opportunity for / of doing something / to do something ) cơ hội, thời cơ"
    ],
    "hash_code_list_mean": "1435249450",
    "list_img": [
      {
        "link_thumb": "https://live.staticflickr.com/65535/51809345516_452e2c734e_n.jpg",
        "link_img": "https://live.staticflickr.com/65535/51809345516_a5d718e3da_o.png",
        "id_image": "opportunity_1900254"
      },
      {
        "link_thumb": "https://live.staticflickr.com/65535/51809460253_823c6b2164_n.jpg",
        "link_img": "https://live.staticflickr.com/65535/51809460253_882d86a4e8_o.png",
        "id_image": "opportunity_1900267"
      },
      {
        "link_thumb": "https://live.staticflickr.com/65535/51810082885_3ebd973a26_n.jpg",
        "link_img": "https://live.staticflickr.com/65535/51810082885_2165d0ca5d_o.png",
        "id_image": "opportunity_3447933"
      },
      {
        "link_thumb": "https://live.staticflickr.com/65535/51809700559_53a22d9bc9_n.jpg",
        "link_img": "https://live.staticflickr.com/65535/51809700559_66366353be_o.png",
        "id_image": "opportunity_6064806"
      }
    ],
    "hash_code_list_img": "-1674735861",
    "list_example": [
      "to have no /little /not much opportunity for hearing good music",
      "a great /golden /marvellous opportunity to travel",
      "I had no opportunity to discuss it with her",
      "to seize an opportunity to do something",
      "let me take this opportunity to say a few words",
      "we took the opportunity of visiting the palace"
    ],
    "hash_code_list_example": "-1677267997"
  },
  {
    "link_it": "https://github.com/lmbstudiocontact/lv_dmean_3500_it_1/raw/main/explosion_lv_dmean_3500_it.json",
    "id_item": "explosion_lv_dmean_3500_it",
    "id_album": "570943489",
    "english": "explosion",
    "list_mean": [
      "sự nổ; sự nổ bùng (cơn giận)",
      "tiếng nổ",
      "(từ Mỹ,nghĩa Mỹ) sự phát triển ồ ạt và nhanh chóng"
    ],
    "hash_code_list_mean": "156169838",
    "list_img": [
      {
        "link_thumb": "https://live.staticflickr.com/65535/51809456528_bd87b25d35_n.jpg",
        "link_img": "https://live.staticflickr.com/65535/51809456528_b8f29d403b_o.png",
        "id_image": "explosion_209231"
      },
      {
        "link_thumb": "https://live.staticflickr.com/65535/51808386707_42a80af91a_n.jpg",
        "link_img": "https://live.staticflickr.com/65535/51808386707_e964f20a97_o.png",
        "id_image": "explosion_2737916"
      },
      {
        "link_thumb": "https://live.staticflickr.com/65535/51808386672_96fd93b104_n.jpg",
        "link_img": "https://live.staticflickr.com/65535/51808386672_07c00e84ee_o.png",
        "id_image": "explosion_3937186"
      }
    ],
    "hash_code_list_img": "-1015282156",
    "list_example": [
      "population explosion"
    ],
    "hash_code_list_example": "-1335144927"
  },
  {
    "link_it": "https://github.com/lmbstudiocontact/lv_dmean_3500_it_2/raw/main/plantation_lv_dmean_3500_it.json",
    "id_item": "plantation_lv_dmean_3500_it",
    "id_album": "570943489",
    "english": "plantation",
    "list_mean": [
      "khu đất trồng cây, vườn ươm; cây trồng",
      "đồn điền (bông, cà phê...)",
      "(sử học) sự di dân sang thuộc địa",
      "(sử học) thuộc địa"
    ],
    "hash_code_list_mean": "1194751589",
    "list_img": [
      {
        "link_thumb": "https://live.staticflickr.com/65535/51809697859_1fa5482688_n.jpg",
        "link_img": "https://live.staticflickr.com/65535/51809697859_792704a86d_o.png",
        "id_image": "plantation_1191617"
      },
      {
        "link_thumb": "https://live.staticflickr.com/65535/51809342551_c922ca1dcf_n.jpg",
        "link_img": "https://live.staticflickr.com/65535/51809342551_7700285622_o.png",
        "id_image": "plantation_1590710"
      }
    ],
    "hash_code_list_img": "1318361928",
    "list_example": [
      "a plantation manager"
    ],
    "hash_code_list_example": "-1421394123"
  },
  {
    "link_it": "https://github.com/lmbstudiocontact/lv_dmean_3500_it_0/raw/main/brain_lv_dmean_3500_it.json",
    "id_item": "brain_lv_dmean_3500_it",
    "id_album": "570943489",
    "english": "brain",
    "list_mean": [
      "óc; não",
      "trí tuệ; trí lực; trí thông minh",
      "người thông minh; người trí thức",
      "( the brains ) người giỏi nhất trong một nhóm",
      "giết bằng cách đánh mạnh vào đầu; đánh vỡ đầu"
    ],
    "hash_code_list_mean": "1016189077",
    "list_img": [
      {
        "link_thumb": "https://live.staticflickr.com/65535/51808363462_fcb0a6598b_n.jpg",
        "link_img": "https://live.staticflickr.com/65535/51808363462_34a8dc39b2_o.png",
        "id_image": "brains_2451242"
      },
      {
        "link_thumb": "https://live.staticflickr.com/65535/51808363442_5d576bc84a_n.jpg",
        "link_img": "https://live.staticflickr.com/65535/51808363442_39984e0e6f_o.png",
        "id_image": "brains_2451257"
      },
      {
        "link_thumb": "https://live.staticflickr.com/65535/51809673749_9e58910032_n.jpg",
        "link_img": "https://live.staticflickr.com/65535/51809673749_a141d85c54_o.png",
        "id_image": "brain_286484"
      }
    ],
    "hash_code_list_img": "167993079",
    "list_example": [
      "the brain is the centre of the nervous system",
      "brain surgery"
    ],
    "hash_code_list_example": "-1436962096"
  },
  {
    "link_it": "https://github.com/lmbstudiocontact/lv_dmean_3500_it_3/raw/main/upgrade_lv_dmean_3500_it.json",
    "id_item": "upgrade_lv_dmean_3500_it",
    "id_album": "570943489",
    "english": "upgrade",
    "list_mean": [
      "cải tạo giống (gia súc)",
      "nâng cao chất lượng (sản phẩm)",
      "đưa lên cấp bậc cao hơn, nâng cấp, đề bạt",
      "(từ Mỹ, nghĩa Mỹ) dốc đi lên"
    ],
    "hash_code_list_mean": "385524310",
    "list_img": [
      {
        "link_thumb": "https://live.staticflickr.com/65535/51809466388_d062bf6208_n.jpg",
        "link_img": "https://live.staticflickr.com/65535/51809466388_7531bbd1a1_o.png",
        "id_image": "upgrade_2790406"
      },
      {
        "link_thumb": "https://live.staticflickr.com/65535/51809351916_7631b5dbb2_n.jpg",
        "link_img": "https://live.staticflickr.com/65535/51809351916_b13cd0e491_o.png",
        "id_image": "upgrade_3231374"
      },
      {
        "link_thumb": "https://live.staticflickr.com/65535/51810089045_821b6f1d9e_n.jpg",
        "link_img": "https://live.staticflickr.com/65535/51810089045_181dd6d613_o.png",
        "id_image": "upgrade_5956427"
      }
    ],
    "hash_code_list_img": "-1473534689",
    "list_example": [
      "She was upgraded to (the post of ) sales director"
    ],
    "hash_code_list_example": "-1193730526"
  },
  {
    "link_it": "https://github.com/lmbstudiocontact/lv_dmean_3500_it_2/raw/main/pocket_lv_dmean_3500_it.json",
    "id_item": "pocket_lv_dmean_3500_it",
    "id_album": "570943489",
    "english": "pocket",
    "list_mean": [
      "túi (quần, áo); túi đựng (trong xe hơi, vali..)",
      "bao ( 75 kg)",
      "túi tiền",
      "nhóm biệt lập; ổ (nhất là trong chiến đấu)",
      "(thể dục thể thao) túi lưới, túi hứng bi (cạnh bàn bi-a)",
      "(ngành mỏ) túi quặng, túi khí độc; túi, hốc nhỏ ở trong hốc đá (chứa vàng, than..)",
      "(hàng không) lỗ hổng không khí (như) air pocket",
      "(từ Mỹ,nghĩa Mỹ) ngõ cụt",
      "(thể dục,thể thao) thế bị chèn, thế bị càn (của một vận động viên trong cuộc đua)",
      "bỏ (cái gì) vào túi",
      "đút túi; giữ, lấy (cái gì)",
      "(nghĩa bóng) cam chịu, nuốt",
      "(thể dục,thể thao) thọc (quả bi) vào túi lưới",
      "(thể dục,thể thao) chèn, cản (đối thủ trong cuộc đấu)"
    ],
    "hash_code_list_mean": "-1032548398",
    "list_img": [
      {
        "link_thumb": "https://live.staticflickr.com/65535/51810076410_8ebcdf88ef_n.jpg",
        "link_img": "https://live.staticflickr.com/65535/51810076410_175b4f11fc_o.png",
        "id_image": "pocket_2803510"
      },
      {
        "link_thumb": "https://live.staticflickr.com/65535/51809339221_f8c3e4991e_n.jpg",
        "link_img": "https://live.staticflickr.com/65535/51809339221_92d5a38b31_o.png",
        "id_image": "pocket_3655751"
      },
      {
        "link_thumb": "https://live.staticflickr.com/65535/51810076440_fa445966eb_n.jpg",
        "link_img": "https://live.staticflickr.com/65535/51810076440_7dcb1336ee_o.png",
        "id_image": "pocket_532027"
      }
    ],
    "hash_code_list_img": "201610460",
    "list_example": [
      "a pocket dictionary",
      "a pocket edition",
      "a pocket of hops",
      "to pocket one's anger"
    ],
    "hash_code_list_example": "-688819393"
  },
  {
    "link_it": "https://github.com/lmbstudiocontact/lv_dmean_3500_it_3/raw/main/stumble_lv_dmean_3500_it.json",
    "id_item": "stumble_lv_dmean_3500_it",
    "id_album": "570943489",
    "english": "stumble",
    "list_mean": [
      "sự vấp, sự sẩy chân, sự trượt chân; sự súyt ngã",
      "sự vấp (khi nói, chơi nhạc...)",
      "(từ Mỹ,nghĩa Mỹ) sự lầm lỡ, sự sai lầm",
      "vấp, sẩy chân, trượt chân, súyt ngã",
      "( + over , through ) vấp (khi nói, chơi nhạc..)",
      "ngần ngại, lưỡng lực (trước một việc gì)",
      "( + about , along , around ) đi nghiêng ngả; đi loạng choạng",
      "tình cờ gặp",
      "(từ Mỹ,nghĩa Mỹ) lầm lỡ, sai lầm"
    ],
    "hash_code_list_mean": "-242523609",
    "list_img": [
      {
        "link_thumb": "https://live.staticflickr.com/65535/51809696219_29feb060af_n.jpg",
        "link_img": "https://live.staticflickr.com/65535/51809696219_fd6e7b8588_o.png",
        "id_image": "stumble_2557007"
      }
    ],
    "hash_code_list_img": "1056439075",
    "list_example": [
      "to stumble in a speech",
      "to stumble upon somebody"
    ],
    "hash_code_list_example": "2128259521"
  },
  {
    "link_it": "https://github.com/lmbstudiocontact/lv_dmean_3500_it_0/raw/main/army_lv_dmean_3500_it.json",
    "id_item": "army_lv_dmean_3500_it",
    "id_album": "570943489",
    "english": "army",
    "list_mean": [
      "quân đội",
      "đoàn, đám đông, nhiều vô số"
    ],
    "hash_code_list_mean": "-1826433600",
    "list_img": [
      {
        "link_thumb": "https://live.staticflickr.com/65535/51809661029_62e3303cbe_n.jpg",
        "link_img": "https://live.staticflickr.com/65535/51809661029_ab28026c89_o.png",
        "id_image": "army_1733969"
      },
      {
        "link_thumb": "https://live.staticflickr.com/65535/51809420613_9269341736_n.jpg",
        "link_img": "https://live.staticflickr.com/65535/51809420613_41110bb692_o.png",
        "id_image": "army_1750028"
      }
    ],
    "hash_code_list_img": "-1847578849",
    "list_example": [
      "an army of workers"
    ],
    "hash_code_list_example": "451420155"
  },
  {
    "link_it": "https://github.com/lmbstudiocontact/lv_dmean_3500_it_2/raw/main/period_lv_dmean_3500_it.json",
    "id_item": "period_lv_dmean_3500_it",
    "id_album": "570943489",
    "english": "period",
    "list_mean": [
      "kỳ, thời kỳ, thời gian",
      "thời kỳ, giai đoạn, thời đại (của lịch sử, đời người, nền văn minh..)",
      "(địa chất) kỷ, thời kỳ (quãng thời gian trong quá trình phát triển của bề mặt trái đất)",
      "tiết (học)",
      "huyết từ tử cung của phụ nữ chảy ra hàng tháng; kinh nguyệt; kỳ hành kinh",
      "(toán học); (vật lý); (thiên văn học) chu kỳ",
      "(ngôn ngữ học) câu nhiều đoạn",
      "(ngôn ngữ học) chấm câu; dấu chấm câu",
      "(thuộc) thời kỳ đã qua; mang tính chất thời đại, mang màu sắc thời đại (đã qua)"
    ],
    "hash_code_list_mean": "-1069570105",
    "list_img": [
      {
        "link_thumb": "https://live.staticflickr.com/65535/51808365462_7befbcc5d7_n.jpg",
        "link_img": "https://live.staticflickr.com/65535/51808365462_35189b1220_o.png",
        "id_image": "period_4277930"
      },
      {
        "link_thumb": "https://live.staticflickr.com/65535/51809320491_4ce173a9f5_n.jpg",
        "link_img": "https://live.staticflickr.com/65535/51809320491_f40f3c2820_o.png",
        "id_image": "period_5746612"
      }
    ],
    "hash_code_list_img": "1756239987",
    "list_example": [
      "a period of rest",
      "a period of three years",
      "a teaching period of 45 minutes",
      "period pains",
      "period of a circulating decimal",
      "period of oscillation"
    ],
    "hash_code_list_example": "-105991577"
  },
  {
    "link_it": "https://github.com/lmbstudiocontact/lv_dmean_3500_it_0/raw/main/actor_lv_dmean_3500_it.json",
    "id_item": "actor_lv_dmean_3500_it",
    "id_album": "570943489",
    "english": "actor",
    "list_mean": [
      "diễn viên (kịch, tuồng, chèo, (điện ảnh)...); kép, kép hát",
      "(từ hiếm,nghĩa hiếm) người làm (một việc gì)"
    ],
    "hash_code_list_mean": "381064628",
    "list_img": [
      {
        "link_thumb": "https://live.staticflickr.com/65535/51809677219_293ebcac11_n.jpg",
        "link_img": "https://live.staticflickr.com/65535/51809677219_d8df96461a_o.png",
        "id_image": "actor_323981"
      },
      {
        "link_thumb": "https://live.staticflickr.com/65535/51809677164_17aa02ced2_n.jpg",
        "link_img": "https://live.staticflickr.com/65535/51809677164_8b2fdf056c_o.png",
        "id_image": "actor_4695680"
      },
      {
        "link_thumb": "https://live.staticflickr.com/65535/51810058845_341cd0a468_n.jpg",
        "link_img": "https://live.staticflickr.com/65535/51810058845_14b210148a_o.png",
        "id_image": "actor_6036699"
      },
      {
        "link_thumb": "https://live.staticflickr.com/65535/51808366952_d2d635704a_n.jpg",
        "link_img": "https://live.staticflickr.com/65535/51808366952_c0cd020567_o.png",
        "id_image": "actor_6347173"
      }
    ],
    "hash_code_list_img": "-1056307593",
    "list_example": [
      "film actor",
      "a bad actor"
    ],
    "hash_code_list_example": "-1923166301"
  },
  {
    "link_it": "https://github.com/lmbstudiocontact/lv_dmean_3500_it_3/raw/main/torrent_lv_dmean_3500_it.json",
    "id_item": "torrent_lv_dmean_3500_it",
    "id_album": "570943489",
    "english": "torrent",
    "list_mean": [
      "dòng nước chảy xiết, dòng nước lũ; cơn mưa rất to",
      "sự phun ra mạnh mẽ; một tràng (chửi rủa, lăng mạ..)"
    ],
    "hash_code_list_mean": "-422970974",
    "list_img": [
      {
        "link_thumb": "https://live.staticflickr.com/65535/51808387852_f212bc376e_n.jpg",
        "link_img": "https://live.staticflickr.com/65535/51808387852_27f037d99a_o.png",
        "id_image": "torrent_2800123"
      }
    ],
    "hash_code_list_img": "1068773094",
    "list_example": [
      "a torrent of abuse"
    ],
    "hash_code_list_example": "529089867"
  },
  {
    "link_it": "https://github.com/lmbstudiocontact/lv_dmean_3500_it_2/raw/main/peg_lv_dmean_3500_it.json",
    "id_item": "peg_lv_dmean_3500_it",
    "id_album": "570943489",
    "english": "peg",
    "list_mean": [
      "cái chốt; cái móc; cái mắc",
      "cái mắc (áo, mũ..)",
      "cọc buộc lều (như) tent-peg",
      "cọc đánh dấu (đất..)",
      "cái ngạc",
      "miếng gỗ chèn, bít (lỗ thùng...)",
      "núm lên dây đàn (như) tuning peg",
      "cái kẹp phơi quần áo (như) clothes peg",
      "chân giả (thường) bằng gỗ; người có chân giả (như) peg leg",
      "rượu cônhắc pha xô-đa",
      "(nghĩa bóng) cớ, lý do, cơ hội; đề tài",
      "đóng chốt, đóng cọc (để giữ chặt)",
      "( + down ) ghìm chặt, hạn chế, câu thúc, kiềm chế",
      "ghìm không cho lên xuống (giá hối đoái)",
      "ổn định (giá cả...)",
      "(từ lóng) ném (đá...)",
      "ghi (điểm số) bằng chốt (chơi kipbi)",
      "(từ Mỹ,nghĩa Mỹ) vạch mặt chỉ tên là",
      "cầm chốt đánh vào, cầm cọc đánh vào; cầm chốt nhắm vào, cầm cọc nhắm vào; đâm thủng bằng chốt, đâm thủng bằng cọc",
      "ném đá vào"
    ],
    "hash_code_list_mean": "-332902126",
    "list_img": [
      {
        "link_thumb": "https://live.staticflickr.com/65535/51809438323_f5c95fd20c_n.jpg",
        "link_img": "https://live.staticflickr.com/65535/51809438323_c66af93a9b_o.png",
        "id_image": "peg_4636779"
      }
    ],
    "hash_code_list_img": "528162185",
    "list_example": [
      "to peg someone down to rules",
      "to peg someone down to his work",
      "to peg somebody as a scoundred"
    ],
    "hash_code_list_example": "1526454614"
  },
  {
    "link_it": "https://github.com/lmbstudiocontact/lv_dmean_3500_it_2/raw/main/processor_lv_dmean_3500_it.json",
    "id_item": "processor_lv_dmean_3500_it",
    "id_album": "570943489",
    "english": "processor",
    "list_mean": [
      "máy chế biến, máy xử lý",
      "bộ xử lý trong máy tính"
    ],
    "hash_code_list_mean": "-345999012",
    "list_img": [
      {
        "link_thumb": "https://live.staticflickr.com/65535/51809322781_f945b6acbc_n.jpg",
        "link_img": "https://live.staticflickr.com/65535/51809322781_fbd9ee6710_o.png",
        "id_image": "processor_2620603"
      },
      {
        "link_thumb": "https://live.staticflickr.com/65535/51810059485_e53262f5b8_n.jpg",
        "link_img": "https://live.staticflickr.com/65535/51810059485_da64a9ed64_o.png",
        "id_image": "processor_3205476"
      },
      {
        "link_thumb": "https://live.staticflickr.com/65535/51809437923_826f315cff_n.jpg",
        "link_img": "https://live.staticflickr.com/65535/51809437923_7bee668b74_o.png",
        "id_image": "processor_6343570"
      }
    ],
    "hash_code_list_img": "2020503821",
    "list_example": [
      "a food processor"
    ],
    "hash_code_list_example": "-466978546"
  },
  {
    "link_it": "https://github.com/lmbstudiocontact/lv_dmean_3500_it_3/raw/main/sow_lv_dmean_3500_it.json",
    "id_item": "sow_lv_dmean_3500_it",
    "id_album": "570943489",
    "english": "sow",
    "list_mean": [
      "gieo hạt, xạ",
      "(nghĩa bóng) gieo rắc, gây mầm, đưa ra (cảm xúc, ý kiến..)",
      "lợn nái; lợn cái hoàn toàn trưởng thành",
      "(động vật học) mọt gỗ (như) sow-bug",
      "rãnh (cho kim loại nấu chảy ra khuôn); kim loại cứng lại ở rãnh"
    ],
    "hash_code_list_mean": "438367880",
    "list_img": [
      {
        "link_thumb": "https://live.staticflickr.com/65535/51809440308_0c5e667f2b_n.jpg",
        "link_img": "https://live.staticflickr.com/65535/51809440308_abf810dc70_o.png",
        "id_image": "sow_3319281"
      },
      {
        "link_thumb": "https://live.staticflickr.com/65535/51809440273_c1f484aa0b_n.jpg",
        "link_img": "https://live.staticflickr.com/65535/51809440273_205e025f85_o.png",
        "id_image": "sow_6041419"
      }
    ],
    "hash_code_list_img": "-287158364",
    "list_example": [
      "to sow land with maize",
      "to sow the seeds of dissension"
    ],
    "hash_code_list_example": "-1292065755"
  },
  {
    "link_it": "https://github.com/lmbstudiocontact/lv_dmean_3500_it_2/raw/main/mute_lv_dmean_3500_it.json",
    "id_item": "mute_lv_dmean_3500_it",
    "id_album": "570943489",
    "english": "mute",
    "list_mean": [
      "câm, thầm lặng, lặng thinh, ngầm, không nói được nên lời, im hơi lặng tiếng",
      "người câm",
      "(sân khấu) vai tuồng câm",
      "(ngôn ngữ học) nguyên âm câm; phụ âm câm",
      "người đi đưa ma thuê; người khóc mướn",
      "người đầy tớ câm",
      "(âm nhạc) cái chặn tiếng",
      "(âm nhạc) chặn tiếng",
      "(âm nhạc) lắp cái chặn tiếng",
      "(từ Mỹ,nghĩa Mỹ) làm câm",
      "ỉa (chim)"
    ],
    "hash_code_list_mean": "1779406245",
    "list_img": [
      {
        "link_thumb": "https://live.staticflickr.com/65535/51809445243_c249823d7b_n.jpg",
        "link_img": "https://live.staticflickr.com/65535/51809445243_1edfc40e28_o.png",
        "id_image": "mute_1112541"
      },
      {
        "link_thumb": "https://live.staticflickr.com/65535/51809445203_59f2141af8_n.jpg",
        "link_img": "https://live.staticflickr.com/65535/51809445203_4fa5a7260e_o.png",
        "id_image": "mute_2831073"
      },
      {
        "link_thumb": "https://live.staticflickr.com/65535/51810067065_d1236c223a_n.jpg",
        "link_img": "https://live.staticflickr.com/65535/51810067065_fd589bce6b_o.png",
        "id_image": "mute_6212371"
      }
    ],
    "hash_code_list_img": "-1701075538",
    "list_example": [
      "in mute love",
      "mute e"
    ],
    "hash_code_list_example": "1937448897"
  },
  {
    "link_it": "https://github.com/lmbstudiocontact/lv_dmean_3500_it_1/raw/main/light_lv_dmean_3500_it.json",
    "id_item": "light_lv_dmean_3500_it",
    "id_album": "570943489",
    "english": "light",
    "list_mean": [
      "ánh sáng, ánh sáng mặt trời, ánh sáng ban ngày",
      "nguồn ánh sáng, đèn đuốc",
      "lửa, tia lửa; diêm, đóm",
      "( số nhiều) sự hiểu biết, trí thức, trí tuệ, chân lý",
      "trạng thái, phương diện, quan niệm",
      "sự soi sáng, sự làm sáng tỏ; ( số nhiều) những sự kiện làm sáng tỏ, những phát minh làm sáng tỏ",
      "(tôn giáo) ánh sáng của thượng đế",
      "sinh khí, sự tinh anh; ánh mắt; (thơ ca) sự nhìn",
      "( số nhiều) (từ lóng) đôi mắt",
      "( số nhiều) phổi súc vật (cừu, lợn...) (dùng làm thức ăn cho chó, mèo...)",
      "cửa, lỗ sáng",
      "( số nhiều) khả năng",
      "(nghệ thuật) chỗ sáng trong bức tranh",
      "đốt, thắp, châm, nhóm",
      "soi sáng, chiếu sáng",
      "( (thường) + up ) làm cho rạng lên, làm cho sáng ngời lên (nét mặt, khoé mắt)",
      "( (thường) + up ) lên đèn, thắp đèn",
      "thắp, đốt, bắt lửa, bén lửa",
      "( (thường) + up ) sáng ngời, tươi lên",
      "nhẹ, nhẹ nhàng",
      "(nói về màu sắc) nhạt",
      "nhanh nhẹn",
      "nhẹ nhàng, thanh thoát, dịu dàng, thư thái",
      "khinh suất, nông nổi, nhẹ dạ, bộp chộp; lăng nhăng; lẳng lơ, đĩ thoã",
      "tầm thường, không quan trọng"
    ],
    "hash_code_list_mean": "-683682352",
    "list_img": [
      {
        "link_thumb": "https://live.staticflickr.com/65535/51808387602_72ccc426b8_n.jpg",
        "link_img": "https://live.staticflickr.com/65535/51808387602_2f878e2468_o.png",
        "id_image": "light_3102361"
      },
      {
        "link_thumb": "https://live.staticflickr.com/65535/51809457348_28a1f45396_n.jpg",
        "link_img": "https://live.staticflickr.com/65535/51809457348_864bc4c749_o.png",
        "id_image": "light_3562935"
      },
      {
        "link_thumb": "https://live.staticflickr.com/65535/51809342601_9ff482c069_n.jpg",
        "link_img": "https://live.staticflickr.com/65535/51809342601_a785767f31_o.png",
        "id_image": "light_546020"
      }
    ],
    "hash_code_list_img": "300817145",
    "list_example": [
      "in the light of these facts",
      "give me a light , please",
      "men of light and leading",
      "to light a fire",
      "it is time to light up",
      "this lamp does not light well",
      "as light as a feather",
      "light food",
      "light sleep",
      "a light sleeper",
      "a light task",
      "a light punishment",
      "light wine",
      "light ship",
      "light marching order",
      "light cavalry",
      "a light blue shirt",
      "to be light of foot",
      "light touch",
      "with a light hand",
      "with a light heart",
      "light music",
      "light comedy",
      "a light woman",
      "a light talk",
      "to tread light on the grass"
    ],
    "hash_code_list_example": "1584093369"
  },
  {
    "link_it": "https://github.com/lmbstudiocontact/lv_dmean_3500_it_2/raw/main/mother_lv_dmean_3500_it.json",
    "id_item": "mother_lv_dmean_3500_it",
    "id_album": "570943489",
    "english": "mother",
    "list_mean": [
      "mẹ (của một đứa trẻ hoặc một con vật)",
      "(cách gọi) người phụ nữ đứng đầu một cộng đồng của đạo Thiên chúa; Mẹ",
      "(cách gọi một người đàn bà có tuổi); mẹ",
      "nguồn gốc, nguyên nhân",
      "chăm sóc ( ai/cái gì) như một người mẹ; nuôi dạy",
      "đối xử tốt/chu đáo với ai",
      "gây, tạo, gây ra, gây nên"
    ],
    "hash_code_list_mean": "1116500729",
    "list_img": [
      {
        "link_thumb": "https://live.staticflickr.com/65535/51809450493_aae6f0b1d4_n.jpg",
        "link_img": "https://live.staticflickr.com/65535/51809450493_cf1cf1be79_o.png",
        "id_image": "mother_325663"
      },
      {
        "link_thumb": "https://live.staticflickr.com/65535/51809335491_ce5a56fb83_n.jpg",
        "link_img": "https://live.staticflickr.com/65535/51809335491_c87cb1c4a9_o.png",
        "id_image": "mother_819074"
      }
    ],
    "hash_code_list_img": "1440283447",
    "list_example": [
      "look how the mother chimpanzee cares for her young"
    ],
    "hash_code_list_example": "539413242"
  },
  {
    "link_it": "https://github.com/lmbstudiocontact/lv_dmean_3500_it_1/raw/main/fail_lv_dmean_3500_it.json",
    "id_item": "fail_lv_dmean_3500_it",
    "id_album": "570943489",
    "english": "fail",
    "list_mean": [
      "sự hỏng thi",
      "quên; lơ là hoặc không có khả năng (làm cái gì)",
      "không đủ cho (ai); chấm dứt hoặc thiếu khi ai vẫn còn đang cần đến hoặc đang được mong đợi",
      "(về sức khoẻ, thị lực) trở nên yếu",
      "hỏng, không chạy nữa",
      "phá sản; vỡ nợ",
      "thất bại",
      "đánh trượt (một thí sinh)"
    ],
    "hash_code_list_mean": "-1183519219",
    "list_img": [
      {
        "link_thumb": "https://live.staticflickr.com/65535/51809452633_f62207e6ce_n.jpg",
        "link_img": "https://live.staticflickr.com/65535/51809452633_c823d4f660_o.png",
        "id_image": "failed_3188157"
      },
      {
        "link_thumb": "https://live.staticflickr.com/65535/51810074745_43e6013e68_n.jpg",
        "link_img": "https://live.staticflickr.com/65535/51810074745_bcec20d42e_o.png",
        "id_image": "failed_4313065"
      },
      {
        "link_thumb": "https://live.staticflickr.com/65535/51810074810_24729392f6_n.jpg",
        "link_img": "https://live.staticflickr.com/65535/51810074810_d88aa3d0ef_o.png",
        "id_image": "fail_5705141"
      }
    ],
    "hash_code_list_img": "1969778579",
    "list_example": [
      "don't fail to let me know",
      "she did not fail to keep her word",
      "words fail me"
    ],
    "hash_code_list_example": "1060645038"
  },
  {
    "link_it": "https://github.com/lmbstudiocontact/lv_dmean_3500_it_3/raw/main/warrior_lv_dmean_3500_it.json",
    "id_item": "warrior_lv_dmean_3500_it",
    "id_album": "570943489",
    "english": "warrior",
    "list_mean": [
      "chiến binh, binh lính",
      "thành viên của một bộ lạc chiến đấu cho bộ lạc"
    ],
    "hash_code_list_mean": "2070902209",
    "list_img": [
      {
        "link_thumb": "https://live.staticflickr.com/65535/51808381957_3386f12b66_n.jpg",
        "link_img": "https://live.staticflickr.com/65535/51808381957_a9758dd72b_o.png",
        "id_image": "warrior_1615657"
      },
      {
        "link_thumb": "https://live.staticflickr.com/65535/51809692179_a389566430_n.jpg",
        "link_img": "https://live.staticflickr.com/65535/51809692179_d89ac88c3f_o.png",
        "id_image": "warrior_2229982"
      },
      {
        "link_thumb": "https://live.staticflickr.com/65535/51809692129_ccd5b7fa66_n.jpg",
        "link_img": "https://live.staticflickr.com/65535/51809692129_969fb07133_o.png",
        "id_image": "warrior_4742477"
      }
    ],
    "hash_code_list_img": "-1548641410",
    "list_example": [
      "Zulu warrior"
    ],
    "hash_code_list_example": "-764844187"
  },
  {
    "link_it": "https://github.com/lmbstudiocontact/lv_dmean_3500_it_2/raw/main/plank_lv_dmean_3500_it.json",
    "id_item": "plank_lv_dmean_3500_it",
    "id_album": "570943489",
    "english": "plank",
    "list_mean": [
      "tấm ván (dài, mỏng, dày từ 50 đến 150 mm, rộng ít nhất là 200 mm để lót sàn nhà..)",
      "(nghĩa bóng) mục, nguyên tắc chủ yếu (của một cương lĩnh, chính sách của một đảng (chính trị))",
      "lát ván (sàn...)",
      "(thông tục) ( + down ) đặt (cái gì) mạnh xuống; trả (tiền) ngay",
      "(từ Mỹ,nghĩa Mỹ) nướng (cá, thịt...) bằng cặp chả"
    ],
    "hash_code_list_mean": "407128497",
    "list_img": [
      {
        "link_thumb": "https://live.staticflickr.com/65535/51809343256_c445512a8a_n.jpg",
        "link_img": "https://live.staticflickr.com/65535/51809343256_dfbc85c85d_o.png",
        "id_image": "planks_972738"
      },
      {
        "link_thumb": "https://live.staticflickr.com/65535/51809698544_ed238764af_n.jpg",
        "link_img": "https://live.staticflickr.com/65535/51809698544_2deb8d14da_o.png",
        "id_image": "plank_972756"
      }
    ],
    "hash_code_list_img": "-624165263",
    "list_example": [
      "to plank down money"
    ],
    "hash_code_list_example": "-150701212"
  },
  {
    "link_it": "https://github.com/lmbstudiocontact/lv_dmean_3500_it_3/raw/main/split_lv_dmean_3500_it.json",
    "id_item": "split_lv_dmean_3500_it",
    "id_album": "570943489",
    "english": "split",
    "list_mean": [
      "nứt, nẻ, chia ra, tách ra",
      "ghẻ, bửa, tách",
      "chia ra từng phần",
      "chia rẽ (ý kiến) về một vấn đề, làm chia rẽ, gây bè phái (trong một đảng phái)",
      "(hoá học); (vật lý) làm vỡ (hạt nhân), tách (phân tử)",
      "nứt, vỡ, nẻ",
      "chia rẽ, phân hoá, không nhất trí",
      "(từ Mỹ,nghĩa Mỹ), (thông tục) chia nhau"
    ],
    "hash_code_list_mean": "1274020175",
    "list_img": [
      {
        "link_thumb": "https://live.staticflickr.com/65535/51808398227_efa443f9c9_n.jpg",
        "link_img": "https://live.staticflickr.com/65535/51808398227_d7d12b8f83_o.png",
        "id_image": "split_3557652"
      },
      {
        "link_thumb": "https://live.staticflickr.com/65535/51809468018_df93172ef6_n.jpg",
        "link_img": "https://live.staticflickr.com/65535/51809468018_3ac308356b_o.png",
        "id_image": "split_6026427"
      },
      {
        "link_thumb": "https://live.staticflickr.com/65535/51809468063_7c5c7ee72c_n.jpg",
        "link_img": "https://live.staticflickr.com/65535/51809468063_6873369fa5_o.png",
        "id_image": "split_868666"
      }
    ],
    "hash_code_list_img": "1031980379",
    "list_example": [
      "to split the job",
      "to split a sum of money",
      "to split on a question"
    ],
    "hash_code_list_example": "1452573927"
  },
  {
    "link_it": "https://github.com/lmbstudiocontact/lv_dmean_3500_it_2/raw/main/mix_lv_dmean_3500_it.json",
    "id_item": "mix_lv_dmean_3500_it",
    "id_album": "570943489",
    "english": "mix",
    "list_mean": [
      "trộn, pha lẫn, hoà lẫn",
      "hoà với; hoà lẫn với",
      "hoà nhập, giao thiệp",
      "sự hoà hợp",
      "hỗn hợp các thành phần được đem bán để làm món ăn"
    ],
    "hash_code_list_mean": "1225666257",
    "list_img": [
      {
        "link_thumb": "https://live.staticflickr.com/65535/51808385347_8b40deefdf_n.jpg",
        "link_img": "https://live.staticflickr.com/65535/51808385347_89cc1a20b1_o.png",
        "id_image": "mixed_1214379"
      },
      {
        "link_thumb": "https://live.staticflickr.com/65535/51809340426_b4786917d1_n.jpg",
        "link_img": "https://live.staticflickr.com/65535/51809340426_06aa7bd790_o.png",
        "id_image": "mix_2289953"
      },
      {
        "link_thumb": "https://live.staticflickr.com/65535/51810077720_1477f43738_n.jpg",
        "link_img": "https://live.staticflickr.com/65535/51810077720_2ed8443dfe_o.png",
        "id_image": "mix_5376878"
      }
    ],
    "hash_code_list_img": "1287140039",
    "list_example": [
      "to mix cement /mortar",
      "to mix a cheese sauce for the fish",
      "to mix a dish of salad",
      "to mix sugar with the flour",
      "to mix the yeast into the flour",
      "to mix the flour and water into a smooth paste",
      "don't mix business with pleasure",
      "if you mix red and yellow , you get orange",
      "he found it hard to mix with his gossipy neighbours",
      "in my everyday job , I have to mix with all sorts of people"
    ],
    "hash_code_list_example": "318350706"
  },
  {
    "link_it": "https://github.com/lmbstudiocontact/lv_dmean_3500_it_3/raw/main/standard_lv_dmean_3500_it.json",
    "id_item": "standard_lv_dmean_3500_it",
    "id_album": "570943489",
    "english": "standard",
    "list_mean": [
      "chuẩn; tiêu chuẩn",
      "trình độ; mức",
      "cờ nghi thức đặc biệt (nhất là cờ mình trung thành, phụng sự)",
      "hình tượng, hình ảnh (khắc, chạm..) được gắn vào cột và được quân đội mang theo ra chiến trường trước đây)",
      "lớp học (ở các trường cấp hai); hạng, thứ (ở trường cấp một)",
      "bản vị (vàng, bạc trong hệ thống tiền tệ)",
      "cột hoặc bệ thẳng đứng (dùng làm vật chống đỡ); trục chống",
      "cây, bụi cây đã được ghép trên một gốc cây thẳng đứng (tương phản với cây bụi, cây leo)",
      "Xtanđa (đơn vị đo gỗ bằng khoảng 4, 500 m 3)",
      "làm tiêu chuẩn, được dùng làm tiêu chuẩn, phù hợp với tiêu chuẩn",
      "trung bình, bình thường, thông thường",
      "được thừa nhận, được chấp nhận rộng rãi (về quyền hạn, giá trị)",
      "chuẩn; được chấp nhận rộng rãi thành loại hình thông dụng (về đánh vần, phát âm..)"
    ],
    "hash_code_list_mean": "1001379611",
    "list_img": [
      {
        "link_thumb": "https://live.staticflickr.com/65535/51810086910_02404a6131_n.jpg",
        "link_img": "https://live.staticflickr.com/65535/51810086910_8a26ca73aa_o.png",
        "id_image": "standard_3342138"
      },
      {
        "link_thumb": "https://live.staticflickr.com/65535/51809349656_6b98cb049d_n.jpg",
        "link_img": "https://live.staticflickr.com/65535/51809349656_c50ab42c72_o.png",
        "id_image": "standard_5208254"
      },
      {
        "link_thumb": "https://live.staticflickr.com/65535/51808394402_0bb92c8a91_n.jpg",
        "link_img": "https://live.staticflickr.com/65535/51808394402_e9a60092e3_o.png",
        "id_image": "standard_5572513"
      }
    ],
    "hash_code_list_img": "1686591771",
    "list_example": [
      "the standard of height required for recruits to the air force",
      "an international standard of weight",
      "a restaurant with a low standard of hygiene",
      "to have /enjoy a high standard of living",
      "his work doesn't reach the standard required",
      "to raise the standard of solidarity",
      "standard rose",
      "standard sizes of paper",
      "standard model of a car",
      "this is the standard textbook on the subject",
      "standard English"
    ],
    "hash_code_list_example": "1886151883"
  },
  {
    "link_it": "https://github.com/lmbstudiocontact/lv_dmean_3500_it_3/raw/main/scotch_lv_dmean_3500_it.json",
    "id_item": "scotch_lv_dmean_3500_it",
    "id_album": "570943489",
    "english": "scotch",
    "list_mean": [
      "(thuộc) người Xcốt-len (như) Scots",
      "(thuộc) xứ Xcốt-len (như) Scottish",
      "( the Scotch ) nhân dân Xcốt-len",
      "( Scotch ) tiếng Xcốt-len",
      "( Scotch ) rượu uýt-xki của Xcốt-len; rượu Xcốt; cốc rượu Xcốt",
      "kết thúc, chấm dứt; chặn đứng, làm ngừng (một kế hoạch..)",
      "(từ cổ, nghĩa cổ) làm bị thương (không giết)",
      "đường kẻ, đường vạch (trên đất để chơi nhảy dây)",
      "(từ cổ,nghĩa cổ) khắc, khía, vạch",
      "cái chèn bánh xe",
      "chèn (bánh xe) lại"
    ],
    "hash_code_list_mean": "2139655298",
    "list_img": [
      {
        "link_thumb": "https://live.staticflickr.com/65535/51810065210_44609c1971_n.jpg",
        "link_img": "https://live.staticflickr.com/65535/51810065210_0788eb7446_o.png",
        "id_image": "scotch_282734"
      },
      {
        "link_thumb": "https://live.staticflickr.com/65535/51809328351_982f9f3171_n.jpg",
        "link_img": "https://live.staticflickr.com/65535/51809328351_408566919f_o.png",
        "id_image": "scotch_645750"
      }
    ],
    "hash_code_list_img": "-2045795515",
    "list_example": [
      "Scotch and soda"
    ],
    "hash_code_list_example": "-2132206969"
  },
  {
    "link_it": "https://github.com/lmbstudiocontact/lv_dmean_3500_it_1/raw/main/environment_lv_dmean_3500_it.json",
    "id_item": "environment_lv_dmean_3500_it",
    "id_album": "570943489",
    "english": "environment",
    "list_mean": [
      "điều kiện, hoàn cảnh tác động đến đời sống của mọi người; môi trường",
      "( the environment ) điều kiện thiên nhiên (không khí, nước, đất đai tásông trong đó); môi sinh"
    ],
    "hash_code_list_mean": "904494316",
    "list_img": [
      {
        "link_thumb": "https://live.staticflickr.com/65535/51809672079_e15a927f69_n.jpg",
        "link_img": "https://live.staticflickr.com/65535/51809672079_3af025fcfc_o.png",
        "id_image": "environment_1075063"
      },
      {
        "link_thumb": "https://live.staticflickr.com/65535/51808361667_e2b0ae6a66_n.jpg",
        "link_img": "https://live.staticflickr.com/65535/51808361667_72573585d9_o.png",
        "id_image": "environment_1530449"
      },
      {
        "link_thumb": "https://live.staticflickr.com/65535/51808361782_82a8c59242_n.jpg",
        "link_img": "https://live.staticflickr.com/65535/51808361782_b0a1d273fe_o.png",
        "id_image": "environment_471515"
      },
      {
        "link_thumb": "https://live.staticflickr.com/65535/51810053865_8f4c6493e8_n.jpg",
        "link_img": "https://live.staticflickr.com/65535/51810053865_20a86311bf_o.png",
        "id_image": "environment_860463"
      },
      {
        "link_thumb": "https://live.staticflickr.com/65535/51810053815_d2c1229d04_n.jpg",
        "link_img": "https://live.staticflickr.com/65535/51810053815_e44492f1f5_o.png",
        "id_image": "environment_992266"
      }
    ],
    "hash_code_list_img": "352560552",
    "list_example": [
      "an unhappy home environment can affect a child's behaviour",
      "a noisy smoke-filled room is not the best environment to work in"
    ],
    "hash_code_list_example": "-1323650992"
  },
  {
    "link_it": "https://github.com/lmbstudiocontact/lv_dmean_3500_it_2/raw/main/plumb_lv_dmean_3500_it.json",
    "id_item": "plumb_lv_dmean_3500_it",
    "id_album": "570943489",
    "english": "plumb",
    "list_mean": [
      "quả dọi, hòn chì",
      "dây dọi; dây dò nước",
      "thế thẳng đứng, độ ngay (của tường...)",
      "thẳng đứng, ngay",
      "(nghĩa bóng) hoàn toàn, đích thật",
      "(nghĩa bóng) đúng, chính xác",
      "(từ lóng) hoàn toàn, tuyệt đối",
      "dò độ sâu (biển, sông...) bằng dây dò; đo (độ sâu) bằng dây dò",
      "(nghĩa bóng) dò, thăm dò, dò xét",
      "làm thẳng đứng (bức tường...)",
      "làm nghề hàn chì"
    ],
    "hash_code_list_mean": "-134820284",
    "list_img": [
      {
        "link_thumb": "https://live.staticflickr.com/65535/51810077050_19e2ee2c18_n.jpg",
        "link_img": "https://live.staticflickr.com/65535/51810077050_c65a5d5379_o.png",
        "id_image": "plumb_3556115"
      }
    ],
    "hash_code_list_img": "2139051113",
    "list_example": [
      "a plumb wall",
      "plumb nonsense",
      "plumb in the centre",
      "plumb crazy",
      "to plumb a mystery"
    ],
    "hash_code_list_example": "-1506509692"
  },
  {
    "link_it": "https://github.com/lmbstudiocontact/lv_dmean_3500_it_2/raw/main/retail_lv_dmean_3500_it.json",
    "id_item": "retail_lv_dmean_3500_it",
    "id_album": "570943489",
    "english": "retail",
    "list_mean": [
      "sự bán lẻ; việc bán lẻ",
      "bán lẻ; mua lẻ",
      "( to retail something at / for something ) bán lẻ; được bán lẻ",
      "thuật lại (chi tiết lời đồn, vụ bê bối...) cho người khác, thường là nhiều lần lặp đi lặp lại"
    ],
    "hash_code_list_mean": "1937855400",
    "list_img": [
      {
        "link_thumb": "https://live.staticflickr.com/65535/51809349616_e6a08cf707_n.jpg",
        "link_img": "https://live.staticflickr.com/65535/51809349616_69df9c29b0_o.png",
        "id_image": "retail_1353752"
      },
      {
        "link_thumb": "https://live.staticflickr.com/65535/51809704269_090367bc2b_n.jpg",
        "link_img": "https://live.staticflickr.com/65535/51809704269_f7e3d3e370_o.png",
        "id_image": "retail_2037284"
      },
      {
        "link_thumb": "https://live.staticflickr.com/65535/51809464268_cfeb84805b_n.jpg",
        "link_img": "https://live.staticflickr.com/65535/51809464268_2075c8af6c_o.png",
        "id_image": "retail_6206766"
      }
    ],
    "hash_code_list_img": "-348995907",
    "list_example": [
      "outlets for the retail of leather goods",
      "the retail price index",
      "retail businesses /traders",
      "retail dealer",
      "do you buy wholesale or retail ?",
      "these hats retail at /for 50 francs"
    ],
    "hash_code_list_example": "851601916"
  },
  {
    "link_it": "https://github.com/lmbstudiocontact/lv_dmean_3500_it_3/raw/main/tongue_lv_dmean_3500_it.json",
    "id_item": "tongue_lv_dmean_3500_it",
    "id_album": "570943489",
    "english": "tongue",
    "list_mean": [
      "cái lưỡi (người)",
      "lưỡi bò... làm thức ăn",
      "tiếng; ngôn ngữ",
      "dải nhô ra, vạt nhô ra",
      "tia lửa nhọn đầu",
      "ngắt âm (sáo, kèn...) bằng lưỡi"
    ],
    "hash_code_list_mean": "-1760696722",
    "list_img": [
      {
        "link_thumb": "https://live.staticflickr.com/65535/51809459093_0a52bda712_n.jpg",
        "link_img": "https://live.staticflickr.com/65535/51809459093_161fda5496_o.png",
        "id_image": "tongue_2688374"
      },
      {
        "link_thumb": "https://live.staticflickr.com/65535/51809344281_b3e15deb38_n.jpg",
        "link_img": "https://live.staticflickr.com/65535/51809344281_9e38519925_o.png",
        "id_image": "tongue_3813083"
      },
      {
        "link_thumb": "https://live.staticflickr.com/65535/51810081755_523afe5988_n.jpg",
        "link_img": "https://live.staticflickr.com/65535/51810081755_d22bf238bf_o.png",
        "id_image": "tongue_599518"
      }
    ],
    "hash_code_list_img": "1389098784",
    "list_example": [
      "he speaks English , but his native tongue is German",
      "the tongue of a shoe",
      "the tongue of a bell",
      "a narrow tongue of land jutting out into the sea"
    ],
    "hash_code_list_example": "-1031960150"
  },
  {
    "link_it": "https://github.com/lmbstudiocontact/lv_dmean_3500_it_0/raw/main/bless_lv_dmean_3500_it.json",
    "id_item": "bless_lv_dmean_3500_it",
    "id_album": "570943489",
    "english": "bless",
    "list_mean": [
      "giáng phúc, ban phúc",
      "làm cho may mắn, làm cho hạnh phúc",
      "tôn sùng",
      "cầu Chúa phù hộ cho"
    ],
    "hash_code_list_mean": "251355689",
    "list_img": [
      {
        "link_thumb": "https://live.staticflickr.com/65535/51810039215_63d3e0c13a_n.jpg",
        "link_img": "https://live.staticflickr.com/65535/51810039215_a55fdefd95_o.png",
        "id_image": "bless_5553126"
      }
    ],
    "hash_code_list_img": "1637577813",
    "list_example": [
      "to be blessed with good health"
    ],
    "hash_code_list_example": "69876866"
  },
  {
    "link_it": "https://github.com/lmbstudiocontact/lv_dmean_3500_it_0/raw/main/capital_lv_dmean_3500_it.json",
    "id_item": "capital_lv_dmean_3500_it",
    "id_album": "570943489",
    "english": "capital",
    "list_mean": [
      "thủ đô; thủ phủ",
      "chữ viết hoa (cũng) capital letter",
      "vốn; tư bản",
      "(kiến trúc) đầu cột",
      "quan hệ đến sinh mạng",
      "chính yếu; trên hết",
      "(nói về chữ) viết hoa",
      "tuyệt diệu; xuất sắc",
      "vô cùng tai hại"
    ],
    "hash_code_list_mean": "-1242398044",
    "list_img": [
      {
        "link_thumb": "https://live.staticflickr.com/65535/51809443783_bef39af277_n.jpg",
        "link_img": "https://live.staticflickr.com/65535/51809443783_6c89825611_o.png",
        "id_image": "capital_1622590"
      },
      {
        "link_thumb": "https://live.staticflickr.com/65535/51809328761_e3ab683a7b_n.jpg",
        "link_img": "https://live.staticflickr.com/65535/51809328761_bd9f5baa69_o.png",
        "id_image": "capital_1900189"
      },
      {
        "link_thumb": "https://live.staticflickr.com/65535/51809683804_f391dd1b84_n.jpg",
        "link_img": "https://live.staticflickr.com/65535/51809683804_9a8b179e7a_o.png",
        "id_image": "capital_2590457"
      },
      {
        "link_thumb": "https://live.staticflickr.com/65535/51809443663_e13c99cddf_n.jpg",
        "link_img": "https://live.staticflickr.com/65535/51809443663_d4eedbccc2_o.png",
        "id_image": "capital_4327409"
      }
    ],
    "hash_code_list_img": "1356696043",
    "list_example": [
      "Hanoi is the capital of Vietnam",
      "Of capital importance",
      "Paris is spelt with a capital ' P'",
      "What a capital idea !",
      "A capital error"
    ],
    "hash_code_list_example": "-300193125"
  },
  {
    "link_it": "https://github.com/lmbstudiocontact/lv_dmean_3500_it_3/raw/main/statue_lv_dmean_3500_it.json",
    "id_item": "statue_lv_dmean_3500_it",
    "id_album": "570943489",
    "english": "statue",
    "list_mean": [
      "tượng (người, vật... bằng gỗ, đá..)"
    ],
    "hash_code_list_mean": "-1489128548",
    "list_img": [
      {
        "link_thumb": "https://live.staticflickr.com/65535/51810085665_c8463b6ecf_n.jpg",
        "link_img": "https://live.staticflickr.com/65535/51810085665_36e24b403a_o.png",
        "id_image": "statue_1193517"
      },
      {
        "link_thumb": "https://live.staticflickr.com/65535/51809703079_a87972ce68_n.jpg",
        "link_img": "https://live.staticflickr.com/65535/51809703079_885f36d406_o.png",
        "id_image": "statue_1354633"
      }
    ],
    "hash_code_list_img": "-301465178",
    "list_example": [
      "erect a statue of the king on a horse"
    ],
    "hash_code_list_example": "-897471277"
  }
]